shell_util/__init__.py
shell_util/cli.py
shell_util/shell.py
shell_util/shell_result.py
shell_util-0.1.9.dist-info/entry_points.txt
shell_util-0.1.9.dist-info/WHEEL
shell_util-0.1.9.dist-info/METADATA
shell_util-0.1.9.dist-info/RECORD
